[
  {
    "id": 1710846226468,
    "category": "music",
    "title": "Music today is garbage",
    "content": "What title says. Music is honestly just garbage these days. I miss the old days!!!",
    "comments": []
  },
  {
    "id": 1710846253872,
    "category": "guitar",
    "title": "How do I barre chords",
    "content": "I have never been able to barre chords. I just can't figure it out. How do I learn it?",
    "comments": [],
    "user": "kalle",
    "img": "hello.img"
  },
  {
    "id": 1710848609598,
    "category": "Food",
    "title": "How do I cook broccoli?",
    "content": "Do I boil it? Fry it? Salt? Pepper?",
    "comments": []
  },
  {
    "id": 1710848905159,
    "category": "Music",
    "title": "What is the best album of the year?",
    "content": "",
    "comments": []
  },
  {
    "id": 1710853579717,
    "category": "Test",
    "title": "Adding a post",
    "content": "",
    "comments": []
  },
  {
    "id": 1710875587052,
    "category": "TypeScript",
    "title": "Jag älskar typescript",
    "content": "Jokes on you hatar det",
    "comments": []
  },
  {
    "id": 1710876398044,
    "category": "TypeScript",
    "title": "Sova",
    "content": "zzzzzzzzzzzzzzzzzzzzzzzzzzzzzzzzzzzzzzzzzzzz",
    "comments": []
  }
]